README.rst
setup.py
enhydris_synoptic/__init__.py
enhydris_synoptic/admin.py
enhydris_synoptic/celery.py
enhydris_synoptic/models.py
enhydris_synoptic/tasks.py
enhydris_synoptic.egg-info/PKG-INFO
enhydris_synoptic.egg-info/SOURCES.txt
enhydris_synoptic.egg-info/dependency_links.txt
enhydris_synoptic.egg-info/requires.txt
enhydris_synoptic.egg-info/top_level.txt
enhydris_synoptic/migrations/0001_initial.py
enhydris_synoptic/migrations/0002_auto_20150813_1545.py
enhydris_synoptic/migrations/0003_auto_20151021_1041.py
enhydris_synoptic/migrations/0004_auto_20151104_1345.py
enhydris_synoptic/migrations/0005_auto_20160421_1119.py
enhydris_synoptic/migrations/0006_auto_20160421_1130.py
enhydris_synoptic/migrations/__init__.py
enhydris_synoptic/templates/synopticbase-default.html
enhydris_synoptic/templates/synopticbase.html
enhydris_synoptic/templates/synopticgroup-default.html
enhydris_synoptic/templates/synopticgroup.html
enhydris_synoptic/templates/synopticgroupstation-default.html
enhydris_synoptic/templates/synopticgroupstation-report.html
enhydris_synoptic/templates/synopticgroupstation.html